cykooz.recipe.idea-0.4-py3.9-nspkg.pth
cykooz/recipe/idea/__init__.py
cykooz/recipe/idea/runtests.py
cykooz/recipe/idea/tests.py
cykooz.recipe.idea-0.4.dist-info/METADATA
cykooz.recipe.idea-0.4.dist-info/WHEEL
cykooz.recipe.idea-0.4.dist-info/entry_points.txt
cykooz.recipe.idea-0.4.dist-info/namespace_packages.txt
cykooz.recipe.idea-0.4.dist-info/top_level.txt
cykooz.recipe.idea-0.4.dist-info/RECORD
