Metadata-Version: 2.1
Name: cykooz.recipe.idea
Version: 0.4
Summary: zc.buildout recipe that creates a file with list of external libraries for PyCharm of IntelliJ IDEA.
Home-page: https://github.com/Cykooz/cykooz-recipe-idea
Author: Kirill Kuzminykh
Author-email: cykooz@gmail.com
License: UNKNOWN
Platform: UNKNOWN
Classifier: Development Status :: 4 - Beta
Classifier: Programming Language :: Python
Classifier: Programming Language :: Python :: 3
Classifier: Programming Language :: Python :: 3.6
Classifier: Programming Language :: Python :: 3.7
Classifier: Programming Language :: Python :: 3.8
Classifier: Programming Language :: Python :: 3.9
Classifier: Programming Language :: Python :: 3.10
Classifier: Programming Language :: Python :: Implementation :: CPython
Classifier: Framework :: Buildout
Classifier: Framework :: Buildout :: Recipe
Classifier: Intended Audience :: Developers
Classifier: License :: OSI Approved :: MIT License
Classifier: License :: OSI Approved :: Apache Software License
Requires-Dist: setuptools
Requires-Dist: zc.buildout
Requires-Dist: zc.recipe.egg
Provides-Extra: test
Requires-Dist: pytest ; extra == 'test'
Requires-Dist: zc.buildout[test] ; extra == 'test'
Requires-Dist: cykooz.testing ; extra == 'test'
